setup.py
myusps/__init__.py
myusps.egg-info/PKG-INFO
myusps.egg-info/SOURCES.txt
myusps.egg-info/dependency_links.txt
myusps.egg-info/requires.txt
myusps.egg-info/top_level.txt