Metadata-Version: 1.1
Name: myusps
Version: 1.2.2
Summary: Python 3 API for My USPS, a way to track packages.
Home-page: https://github.com/happyleavesaoc/python-myusps/
Author: happyleaves
Author-email: happyleaves.tfr@gmail.com
License: MIT
Platform: UNKNOWN
Classifier: License :: OSI Approved :: MIT License
Classifier: Operating System :: OS Independent
Classifier: Programming Language :: Python :: 3
